MANIFEST.in
README.md
pdb_distance.py
pdb_info.py
pdb_prep.py
pdb_prep_all.py
setup.py
version.py
Chemistry/__init__.py
Chemistry/PDB/Sievers.py
Chemistry/PDB/__init__.py
Chemistry/PDB/pdb_atom.py
Chemistry/PDB/pdb_chain.py
Chemistry/PDB/pdb_constants.py
Chemistry/PDB/pdb_model.py
Chemistry/PDB/pdb_obj.py
Chemistry/PDB/pdb_remark.py
Chemistry/PDB/pdb_utils.py
Geometry/__init__.py
Geometry/distance.py
PDB_Distance/__init__.py
PDB_Distance/protein_dimer_distance.py
PDB_Distance/symetric_axis_distance.py
PDB_Prep/__init__.py
PDB_Prep/clean_stages.py
PDB_Prep/diff_uils.py
PDB_Prep/pdb_prep_functions.py
PDB_Prep/pdb_prep_inform.py
Utils/__init__.py
Utils/cli_utils.py
Utils/inform.py
_Tests/GEOMETRY_distance_unit_test.py
_Tests/PDB_pdb_atom_unit_test.py
_Tests/PDB_pdb_chain_unit_test.py
_Tests/PDB_pdb_model_unit_test.py
_Tests/PDB_pdb_obj_unit_test.py
_Tests/PDB_pdb_remark_unit_test.py
_Tests/PDB_pdb_utils_unit_test.py
_Tests/__init__.py
pdb_prep.egg-info/PKG-INFO
pdb_prep.egg-info/SOURCES.txt
pdb_prep.egg-info/dependency_links.txt
pdb_prep.egg-info/entry_points.txt
pdb_prep.egg-info/requires.txt
pdb_prep.egg-info/top_level.txt