Metadata-Version: 1.1
Name: pdb-prep
Version: 0.0.9.8
Summary: pdb utils
Home-page: https://sagivba.github.io/pdb_prep/
Author: Sagiv Barhoom
Author-email: sagivba@gmail.com
License: BSD 2-Clause
Keywords: pdb-files chemistry RSCB proteins
Platform: UNKNOWN
Classifier: Development Status :: 4 - Beta
Classifier: Environment :: Console
Classifier: Intended Audience :: Science/Research
Classifier: License :: OSI Approved :: BSD License
Classifier: Operating System :: OS Independent
Classifier: Programming Language :: Python
Classifier: Programming Language :: Python :: 3.5
Classifier: Topic :: Scientific/Engineering :: Chemistry
